audit_version/__init__.py
audit_version-0.1.0.dist-info/entry_points.txt
audit_version-0.1.0.dist-info/LICENSE
audit_version-0.1.0.dist-info/WHEEL
audit_version-0.1.0.dist-info/METADATA
audit_version-0.1.0.dist-info/RECORD
